genesys/__init__.py
genesys/debug.py
genesys/job_settings.py
genesys/app/__init__.py
genesys/app/config.py
genesys/app/blueprints/__init__.py
genesys/app/blueprints/asset/__init__.py
genesys/app/blueprints/asset/routes.py
genesys/app/blueprints/asset/utils.py
genesys/app/blueprints/index/__init__.py
genesys/app/blueprints/index/routes.py
genesys/app/blueprints/project/__init__.py
genesys/app/blueprints/project/routes.py
genesys/app/blueprints/project/utils.py
genesys/app/blueprints/refresh/__init__.py
genesys/app/blueprints/refresh/routes.py
genesys/app/blueprints/refresh/utils.py
genesys/app/blueprints/task/__init__.py
genesys/app/blueprints/task/routes.py
genesys/app/blueprints/task/utils.py
genesys/app/services/__init__.py
genesys/app/services/files_service.py
genesys/app/services/project_service.py
genesys/app/services/queue_store.py
genesys/app/services/svn_service.py
genesys/app/template_files/blender.blend
genesys/app/template_files/clipstudio.clip
genesys/app/template_files/flstudio.flp
genesys/app/template_files/sketchbook.tif
genesys/app/utils/__init__.py
genesys/app/utils/config_helpers.py
genesys-0.1.7.dist-info/LICENSE
genesys-0.1.7.dist-info/METADATA
genesys-0.1.7.dist-info/WHEEL
genesys-0.1.7.dist-info/top_level.txt
genesys-0.1.7.dist-info/RECORD
