Metadata-Version: 2.1
Name: genesys
Version: 0.1.7
Summary: generates files and dependences for cgi projects
Home-page: https://eaxum.com
Author: Aderemi Adesada
Author-email: adesadaaderemi@gmail.com
License: UNKNOWN
Keywords: cg,asset,shot,api,cg production,asset management
Platform: UNKNOWN
Classifier: Development Status :: 3 - Alpha
Classifier: Environment :: Web Environment
Classifier: Framework :: Flask
Classifier: Intended Audience :: Developers
Classifier: Programming Language :: Python :: 3.10
Classifier: Programming Language :: Python :: Implementation :: CPython
Classifier: Programming Language :: Python :: Implementation :: PyPy
Classifier: Topic :: Multimedia :: Graphics
Requires-Dist: Jinja2 (==3.0.3)
Requires-Dist: Werkzeug (==1.0.1)
Requires-Dist: bpy (==3.4.0)
Requires-Dist: click (==6.7)
Requires-Dist: flask-restful (==0.3.8)
Requires-Dist: flask (==1.1.1)
Requires-Dist: gevent (==21.8.0)
Requires-Dist: gunicorn (==20.1.0)
Requires-Dist: itsdangerous (==2.0.1)
Requires-Dist: redis (==3.5.3)
Requires-Dist: rq (==1.8.0)
Provides-Extra: dev
Requires-Dist: wheel ; extra == 'dev'
Provides-Extra: prod
Requires-Dist: gevent ; extra == 'prod'
Requires-Dist: gunicorn ; extra == 'prod'
Provides-Extra: test
Requires-Dist: fakeredis ; extra == 'test'
Requires-Dist: pytest (==5.2.0) ; extra == 'test'
